recipemd_extract/__init__.py
recipemd_extract/main.py
recipemd_extract/plugins/__init__.py
recipemd_extract/plugins/chefkoch.py
recipemd_extract/plugins/recipe_schema.py
recipemd_extract/plugins/recipe_scrapers.py
recipemd_extract/plugins/seriouseats.py
recipemd_extract/plugins/wprm.py
recipemd_extract-1.1.1.dist-info/METADATA
recipemd_extract-1.1.1.dist-info/WHEEL
recipemd_extract-1.1.1.dist-info/entry_points.txt
recipemd_extract-1.1.1.dist-info/top_level.txt
recipemd_extract-1.1.1.dist-info/RECORD
